pysitech/Calc.py
pysitech/__init__.py
pysitech/poc.py
pysitech-0.0.5.dist-info/METADATA
pysitech-0.0.5.dist-info/WHEEL
pysitech-0.0.5.dist-info/top_level.txt
pysitech-0.0.5.dist-info/RECORD
