Metadata-Version: 2.1
Name: pysitech
Version: 0.0.5
Summary: Dependecy Confusion POC
Home-page: UNKNOWN
Author: Zeyad Abulaban
Author-email: zeyad@sitech.me
License: UNKNOWN
Platform: UNKNOWN
Classifier: Development Status :: 3 - Alpha
Classifier: Intended Audience :: Education
Classifier: Programming Language :: Python :: 2
Classifier: Programming Language :: Python :: 3
Classifier: Operating System :: MacOS :: MacOS X
Classifier: Operating System :: Microsoft :: Windows
Requires-Dist: requests
